{
  "name": "Satsuma Gijutsu",
  "style": {
    "accent": "#30254a",
    "inverted": "#ffffff"
  },
  "cards": [
    {
      "name": "Ronin Class",
      "type": "Torso",
      "tags": ["Light", "Neutrino"],
      "hp": 3,
      "armor": 1,
      "stats": {
        "damage": ["0", "1-2"],
        "cards": [2, 2],
        "speed": [1, 0]
      },
      "actions": ["$satsuma:eject-system"],
      "disabledActions": ["$satsuma:glare"]
    },
    {
      "name": "Samurai Class",
      "type": "Torso",
      "tags": ["Medium", "Neutrino"],
      "hp": 3,
      "armor": 1,
      "stats": {
        "damage": ["0-1", "2-3"],
        "cards": [3, 2]
      },
      "actions": ["$satsuma:eject-system"],
      "rules": ["$generic:inertia-dischargers"],
      "disabledActions": ["$satsuma:glare"]
    },
    {
      "name": "Ashigaru Class",
      "type": "Torso",
      "tags": ["Medium"],
      "hp": 4,
      "armor": 1,
      "stats": {
        "damage": ["0-1", "2-3"],
        "cards": [3, 2]
      },
      "actions": ["$satsuma:eject-system"]
    },
    {
      "name": "Daimyo Class",
      "type": "Torso",
      "tags": ["Heavy"],
      "hp": 4,
      "armor": 2,
      "stats": {
        "damage": ["0-1", "2-3"],
        "cards": [3, 2],
        "speed": [-1, -1]
      },
      "actions": ["$satsuma:eject-system", "$generic:shoulder-bash"]
    },
    {
      "name": "Batta",
      "type": "Propulsion",
      "tags": ["Legs"],
      "restrictions": ["Non-heavy torso"],
      "hp": 2,
      "armor": 1,
      "stats": {
        "damage": ["0", "1"],
        "speed": [6, 4],
        "disabledSpeed": [2]
      },
      "actions": ["$generic:kick"]
    },
    {
      "name": "Hayai",
      "type": "Propulsion",
      "tags": ["Legs"],
      "hp": 3,
      "armor": 1,
      "stats": {
        "damage": ["0-1", "2"],
        "speed": [5, 4],
        "disabledSpeed": [3]
      },
      "actions": ["$generic:kick"]
    },
    {
      "name": "Neutrino Engine",
      "type": "Propulsion",
      "tags": ["Legs", "Neutrino"],
      "restrictions": ["Neutrino Torso"],
      "hp": 3,
      "armor": 1,
      "stats": {
        "damage": ["0-1", "2"],
        "speed": [4, 3],
        "disabledSpeed": [2]
      },
      "actions": ["$generic:overdrive"],
      "disabledActions": ["$generic:overheat"]
    },
    {
      "name": "Yama",
      "type": "Propulsion",
      "tags": ["Tipod", "Support"],
      "hp": 3,
      "armor": 1,
      "stats": {
        "damage": ["0-1", "2"],
        "speed": [4, 3],
        "disabledSpeed": [1]
      },
      "actions": ["$generic:stabilizers"]
    },
    {
      "name": "Hachidori",
      "type": "Propulsion",
      "tags": ["Hovercraft"],
      "hp": 4,
      "armor": 0,
      "stats": {
        "damage": ["0-3"],
        "speed": [4]
      },
      "rules": ["$generic:hover"],
      "disabledRules": ["$generic:immobile"]
    },
    {
      "name": "Supercapacitator",
      "type": "Special",
      "tags": ["Neutrino", "Cards"],
      "restrictions": ["Neutrino Torso"],
      "hp": 2,
      "armor": 1,
      "stats": {
        "damage": ["0-1"],
        "cards": [1]
      },
      "actions": ["$satsuma:seppuku"],
      "disabledActions": ["$generic:overheat"]
    },
    {
      "name": "Neutrino Thrusters",
      "type": "Special",
      "tags": ["Neutrino", "Movement"],
      "restrictions": ["Neutrino Torso"],
      "hp": 2,
      "armor": 1,
      "stats": {
        "damage": ["0-1"],
        "speed": [1]
      },
      "actions": ["$generic:side-dash"],
      "disabledActions": ["$generic:overheat"]
    },
    {
      "name": "Chisso Reito",
      "type": "Special",
      "tags": ["Refrigeration", "Support"],
      "hp": 2,
      "armor": 3,
      "actions": ["$generic:fire-extinguisher", "$generic:vent-steam"],
      "rules": ["$generic:cold-exhaust"]
    },
    {
      "name": "Tate Hatsudenki",
      "type": "Special",
      "tags": ["Support"],
      "hp": 3,
      "armor": 1,
      "actions": ["$generic:shield-up", "$generic:countermeasures"]
    },
    {
      "name": "Satellite Uplink",
      "type": "Special",
      "tags": ["Support"],
      "hp": 2,
      "armor": 2,
      "rules": ["$generic:remote-override", "$generic:supercomputer"]
    },
    {
      "name": "Hypermetal Katana",
      "type": "Left Arm",
      "tags": ["Melee"],
      "hp": 2,
      "armor": 1,
      "actions": ["$generic:slash"],
      "rules": ["$generic:power-surge"]
    },
    {
      "name": "Neutrino Balancer",
      "type": "Left Arm",
      "tags": ["Utility", "Heat"],
      "hp": 3,
      "armor": 1,
      "actions": ["$satsuma:balancer", "$generic:heat-beam"],
      "disabledActions": ["$generic:overheat"]
    },
    {
      "name": "Taiyo Tanto",
      "type": "Left Arm",
      "tags": ["Melee", "Heat"],
      "restrictions": ["Neutrino Torso"],
      "hp": 2,
      "armor": 1,
      "actions": ["$satsuma:sun-slash"],
      "rules": ["$satsuma:heat-transfer"],
      "disabledActions": ["$generic:overheat"]
    },
    {
      "name": "Ryoshi Launcher",
      "type": "Left Arm",
      "tags": ["Ranged"],
      "hp": 2,
      "armor": 1,
      "stats": {
        "damage": ["0", "1"],
        "accuracy": [0, -1]
      },
      "actions": ["$generic:rocket", "$generic:aa-barrage"]
    },
    {
      "name": "Juryoku Generator",
      "type": "Left Arm",
      "tags": ["Control", "Movement"],
      "hp": 3,
      "armor": 1,
      "actions": ["$satsuma:gravity-well", "$generic:pull"],
      "disabledActions": ["$generic:immobilized"]
    },
    {
      "name": "Taiyo Yari",
      "type": "Right Arm",
      "tags": ["Ranged", "Heat"],
      "restrictions": ["Neutrino Torso"],
      "hp": 3,
      "armor": 1,
      "actions": ["$satsuma:sun-lance"],
      "rules": ["$satsuma:heat-transfer"],
      "disabledActions": ["$generic:overheat"]
    },
    {
      "name": "Kaen Hosha-ki",
      "type": "Right Arm",
      "tags": ["Ranged"],
      "hp": 1,
      "armor": 2,
      "actions": ["$generic:flamethrower"],
      "rules": ["$generic:rekindle"],
      "disabledActions": ["$generic:burn"]
    },
    {
      "name": "Accelerator Gatling",
      "type": "Right Arm",
      "tags": ["Ranged"],
      "restrictions": ["Non-light torso"],
      "hp": 3,
      "armor": 2,
      "stats": {
        "damage": [0, 1, 2],
        "accuracy": [0, -1, -2]
      },
      "actions": ["$generic:chain-shot", "$generic:bullet-spray"]
    },
    {
      "name": "Juryoku Beam",
      "type": "Right Arm",
      "tags": ["Control", "Movement"],
      "hp": 3,
      "armor": 2,
      "actions": ["$generic:repulse", "$generic:pull"]
    },
    {
      "name": "Hypermetal Tedate",
      "type": "Right Arm",
      "tags": ["Support"],
      "hp": 1,
      "armor": 4,
      "actions": ["$generic:shield-bash", "$generic:protect"],
      "disabledActions": ["$generic:shield-bash", "$generic:protect"]
    }
  ]
}
